PerDeepKE/__init__.py
PerDeepKE/embedding.py
PerDeepKE/keyword_extraction.py
PerDeepKE/text_segmentation.py
PerDeepKE-0.0.1.dist-info/LICENSE
PerDeepKE-0.0.1.dist-info/METADATA
PerDeepKE-0.0.1.dist-info/WHEEL
PerDeepKE-0.0.1.dist-info/top_level.txt
PerDeepKE-0.0.1.dist-info/RECORD
