Metadata-Version: 2.1
Name: PerDeepKE
Version: 0.0.1
Summary: Easy-to-Use Persian Keyword Extraction with Deep Learning
Author-email: Iman Khani Jazani <imankhanijazani@gmail.com>
Project-URL: Home page, https://github.com/IKJ1992/PerDeepKE
Project-URL: Bug Tracker, https://github.com/IKJ1992/PerDeepKE/issues
Classifier: Programming Language :: Python :: 3
Classifier: License :: OSI Approved :: MIT License
Classifier: Operating System :: OS Independent
Requires-Python: >=3.8
License-File: LICENSE
